[{
    "name": "青春变形记/熊抱青春记(港)/青春养成记(台)",
    "imgSrc": "https://img1.doubanio.com/view/photo/s_ratio_poster/public/p2670448229.jpg",
    "detail": "2022-03-11(美国网络) / 姜晋安 / 吴珊卓 / 艾娃·摩士 / 麦特里伊·拉玛克里斯南 / 朴惠仁 / 奥赖恩·李 / 何炜晴 / 特里斯坦·艾瑞克·陈 / 吴汉章 / 菲尼亚斯·奥康奈尔 / 乔丹·费舍 / 托菲尔-恩戈 / 格雷森·维拉纽瓦 / 乔什·列维 / 洛瑞·坦·齐恩..."
}, {
    "name": "蜘蛛侠：英雄无归/新蜘蛛侠3/蜘蛛侠：无回之战",
    "imgSrc": "https://img9.doubanio.com/view/photo/s_ratio_poster/public/p2730024046.jpg",
    "detail": "2021-12-15(中国台湾) / 2021-12-17(美国) / 汤姆·赫兰德 / 赞达亚 / 本尼迪克特·康伯巴奇 / 雅各布·巴特朗 / 托比·马奎尔 / 安德鲁·加菲尔德 / 玛丽莎·托梅 / 乔恩·费儒 / 本尼迪克特·王 / 威廉·达福 / 阿尔弗雷德·莫里纳 / 托马斯·哈登·丘奇..."
}, {
    "name": "亚当计划/超时空亚当计划(港)/超时空亚当计画(台)",
    "imgSrc": "https://img2.doubanio.com/view/photo/s_ratio_poster/public/p2869545761.jpg",
    "detail": "2022-03-11(美国网络) / 瑞安·雷诺兹 / 沃克·斯科贝尔 / 马克·鲁弗洛 / 詹妮弗·加纳 / 佐伊·索尔达娜 / 凯瑟琳·基纳 / 小亚历克斯·马里亚里 / 布拉克斯顿·比肯 / 卡斯拉·王 / 露西·格斯特 / 唐纳德·沙利斯 / Esther Li / 本·威尔金森..."
}, {
    "name": "美国女孩/AmericanGirl",
    "imgSrc": "https://img2.doubanio.com/view/photo/s_ratio_poster/public/p2703935581.jpg",
    "detail": "2021-10-31(东京国际电影节) / 2021-12-03(中国台湾) / 林嘉欣 / 庄凯勋 / 方郁婷 / 林品彤 / 曾宝仪 / 夏于乔 / 黄镫辉 / 张诗盈 / 蔡嘉茵 / 蔡明修 / 张允曦 / 中国台湾 / 阮凤仪 / 101分钟 / 美国女孩 / 剧情 / 家庭 / 阮凤仪 Feng-I Fiona Roan / 李冰..."
}, {
    "name": "新鲜/绝命邀约",
    "imgSrc": "https://img9.doubanio.com/view/photo/s_ratio_poster/public/p2868322956.jpg",
    "detail": "2022-01-20(圣丹斯电影节) / 2022-03-04(美国网络) / 黛西·埃德加-琼斯 / 塞巴斯蒂安·斯坦 / 乔尼卡·T·吉布斯 / 夏洛特·勒·邦 / 安德丽亚·邦 / 戴奥·奥柯奈伊 / 布瑞特·迪尔 / 阿丽娜·马里斯 / 威廉·贝勒 / 安东尼·英格拉姆 / 约瑟夫·M·科斯塔..."
}, {
    "name": "驾驶我的车/在车上(台)/DriveMyCar",
    "imgSrc": "https://img2.doubanio.com/view/photo/s_ratio_poster/public/p2639821491.jpg",
    "detail": "2021-07-11(戛纳电影节) / 2021-08-20(日本) / 西岛秀俊 / 三浦透子 / 雾岛丽香 / 冈田将生 / 朴有林 / 金大永 / 袁子芸 / 安部聪子 / 吉田大八 / 猪股俊明 / 佩里·迪桑 / 安辉泰 / 岩濑亮 / 谷川昭一朗 / 西庆子 / 铃木咲 / 日本 / dmc.bitters.co.jp..."
}, {
    "name": "瀑布/TheFalls",
    "imgSrc": "https://img2.doubanio.com/view/photo/s_ratio_poster/public/p2678037153.jpg",
    "detail": "2021-09-06(威尼斯电影节) / 2021-09-13(多伦多国际电影节) / 2021-10-29(中国台湾) / 贾静雯 / 王净 / 陈以文 / 李李仁 / 宋少卿 / 刘亮佐 / 杨丽音 / 魏如萱 / 洪小铃 / 张少怀 / 许玮甯 / 黄信尧 / 魏如昀 / 邓志鸿 / 刘冠廷 / 中国台湾 / 钟孟宏..."
}, {
    "name": "世界上最糟糕的人/世界上最烂的人(台)/尤利娅生命的十二段律动",
    "imgSrc": "https://img9.doubanio.com/view/photo/s_ratio_poster/public/p2669034145.jpg",
    "detail": "2021-07-08(戛纳电影节) / 2021-10-13(法国) / 2021-10-15(挪威) / 雷娜特·赖因斯夫 / 安德斯·丹尼尔森·李 / 赫伯特·诺德鲁姆 / 汉斯·奥拉夫·布雷内 / 玛丽亚·嘉西亚·狄·梅奥 / Thea Stabell / Vidar Sandem / 西莉亚·史都斯坦 / 米娅·麦戈文·扎伊尼..."
}, {
    "name": "芬奇/芬奇的旅程/生化",
    "imgSrc": "https://img1.doubanio.com/view/photo/s_ratio_poster/public/p2721066869.jpg",
    "detail": "2021-11-05(美国) / 汤姆·汉克斯 / 卡赖伯·兰德里·琼斯 / 希默斯 / 洛拉·玛汀内斯-康宁安 / 玛丽·瓦根曼 / 斯基特·乌尔里奇 / 萨米拉·威利 / 美国 / 米格尔·萨普什尼克 / 115分钟 / 芬奇 / 剧情 / 科幻 / 克雷格·勒克 Craig Luck / Ivor Powell..."
}, {
    "name": "Tinder诈骗王/Tinder大骗徒",
    "imgSrc": "https://img2.doubanio.com/view/photo/s_ratio_poster/public/p2841987393.jpg",
    "detail": "2022-02-02(美国网络) / 英国 / 菲丽希缇·莫里斯 /  / 114分钟 / Tinder 诈骗王 / 犯罪 / 纪录片 / 英语"
}]